[
  {
    "assetbundleName": "default",
    "id": 1,
    "name": "未設定",
    "seq": 10
  },
  {
    "assetbundleName": "avatar_costume_0001",
    "id": 101,
    "name": "一歌粉絲T恤",
    "seq": 101
  },
  {
    "assetbundleName": "avatar_costume_0002",
    "id": 102,
    "name": "咲希粉絲T恤",
    "seq": 102
  },
  {
    "assetbundleName": "avatar_costume_0003",
    "id": 103,
    "name": "穗波粉絲T恤",
    "seq": 103
  },
  {
    "assetbundleName": "avatar_costume_0004",
    "id": 104,
    "name": "志步粉絲T恤",
    "seq": 104
  },
  {
    "assetbundleName": "avatar_costume_0005",
    "id": 105,
    "name": "實乃理粉絲T恤",
    "seq": 105
  },
  {
    "assetbundleName": "avatar_costume_0006",
    "id": 106,
    "name": "遙粉絲T恤",
    "seq": 106
  },
  {
    "assetbundleName": "avatar_costume_0007",
    "id": 107,
    "name": "愛莉粉絲T恤",
    "seq": 107
  },
  {
    "assetbundleName": "avatar_costume_0008",
    "id": 108,
    "name": "雫粉絲T恤",
    "seq": 108
  },
  {
    "assetbundleName": "avatar_costume_0009",
    "id": 109,
    "name": "心羽粉絲T恤",
    "seq": 109
  },
  {
    "assetbundleName": "avatar_costume_0010",
    "id": 110,
    "name": "杏粉絲T恤",
    "seq": 110
  },
  {
    "assetbundleName": "avatar_costume_0011",
    "id": 111,
    "name": "彰人粉絲T恤",
    "seq": 111
  },
  {
    "assetbundleName": "avatar_costume_0012",
    "id": 112,
    "name": "冬彌粉絲T恤",
    "seq": 112
  },
  {
    "assetbundleName": "avatar_costume_0013",
    "id": 113,
    "name": "司粉絲T恤",
    "seq": 113
  },
  {
    "assetbundleName": "avatar_costume_0014",
    "id": 114,
    "name": "笑夢粉絲T恤",
    "seq": 114
  },
  {
    "assetbundleName": "avatar_costume_0015",
    "id": 115,
    "name": "寧寧粉絲T恤",
    "seq": 115
  },
  {
    "assetbundleName": "avatar_costume_0016",
    "id": 116,
    "name": "類粉絲T恤",
    "seq": 116
  },
  {
    "assetbundleName": "avatar_costume_0017",
    "id": 117,
    "name": "奏粉絲T恤",
    "seq": 117
  },
  {
    "assetbundleName": "avatar_costume_0018",
    "id": 118,
    "name": "真冬粉絲T恤",
    "seq": 118
  },
  {
    "assetbundleName": "avatar_costume_0019",
    "id": 119,
    "name": "繪名粉絲T恤",
    "seq": 119
  },
  {
    "assetbundleName": "avatar_costume_0020",
    "id": 120,
    "name": "瑞希粉絲T恤",
    "seq": 120
  },
  {
    "assetbundleName": "avatar_costume_0021",
    "id": 121,
    "name": "初音未來粉絲T恤",
    "seq": 121
  },
  {
    "assetbundleName": "avatar_costume_0022",
    "id": 122,
    "name": "鏡音鈴粉絲T恤",
    "seq": 122
  },
  {
    "assetbundleName": "avatar_costume_0023",
    "id": 123,
    "name": "鏡音連粉絲T恤",
    "seq": 123
  },
  {
    "assetbundleName": "avatar_costume_0024",
    "id": 124,
    "name": "巡音流歌粉絲T恤",
    "seq": 124
  },
  {
    "assetbundleName": "avatar_costume_0025",
    "id": 125,
    "name": "MEIKO粉絲T恤",
    "seq": 125
  },
  {
    "assetbundleName": "avatar_costume_0026",
    "id": 126,
    "name": "KAITO粉絲T恤",
    "seq": 126
  },
  {
    "assetbundleName": "avatar_costume_0027",
    "id": 127,
    "name": "Leo/need應援服",
    "seq": 127
  },
  {
    "assetbundleName": "avatar_costume_0028",
    "id": 128,
    "name": "MORE MORE JUMP！應援服",
    "seq": 128
  },
  {
    "assetbundleName": "avatar_costume_0029",
    "id": 129,
    "name": "Vivid BAD SQUAD應援服",
    "seq": 129
  },
  {
    "assetbundleName": "avatar_costume_0030",
    "id": 130,
    "name": "Wonderlands×Showtime應援服",
    "seq": 130
  },
  {
    "assetbundleName": "avatar_costume_0031",
    "id": 131,
    "name": "25點，Nightcord見。應援服",
    "seq": 131
  },
  {
    "assetbundleName": "avatar_costume_0032",
    "id": 132,
    "name": "虛擬歌手應援服",
    "seq": 132
  },
  {
    "assetbundleName": "avatar_costume_0038",
    "id": 138,
    "name": "海獺T恤",
    "seq": 138
  },
  {
    "assetbundleName": "avatar_costume_0039",
    "id": 139,
    "name": "我推超讚T恤",
    "seq": 139
  },
  {
    "assetbundleName": "avatar_costume_0040",
    "id": 140,
    "name": "超喜歡糰子T恤",
    "seq": 140
  },
  {
    "assetbundleName": "avatar_costume_0041",
    "id": 141,
    "name": "超喜歡櫻餅T恤",
    "seq": 141
  },
  {
    "assetbundleName": "avatar_costume_0042",
    "id": 142,
    "name": "超喜歡鬆餅T恤",
    "seq": 142
  },
  {
    "assetbundleName": "avatar_costume_0043",
    "id": 143,
    "name": "超喜歡起司蛋糕T恤",
    "seq": 143
  },
  {
    "assetbundleName": "avatar_costume_0044",
    "id": 144,
    "name": "西式婚禮派T恤",
    "seq": 144
  },
  {
    "assetbundleName": "avatar_costume_0045",
    "id": 145,
    "name": "日式婚禮派T恤",
    "seq": 145
  },
  {
    "assetbundleName": "avatar_costume_0046",
    "id": 146,
    "name": "在屋頂吃吧T恤",
    "seq": 146
  },
  {
    "assetbundleName": "avatar_costume_0047",
    "id": 147,
    "name": "在教室吃吧T恤",
    "seq": 147
  },
  {
    "assetbundleName": "avatar_costume_0048",
    "id": 148,
    "name": "想坐在船裡跟著海浪搖擺T恤",
    "seq": 148
  },
  {
    "assetbundleName": "avatar_costume_0049",
    "id": 149,
    "name": "想套著泳圈跟著海浪搖擺T恤",
    "seq": 149
  },
  {
    "assetbundleName": "avatar_costume_0050",
    "id": 150,
    "name": "超喜歡栗子T恤",
    "seq": 150
  },
  {
    "assetbundleName": "avatar_costume_0051",
    "id": 151,
    "name": "超喜歡柿子T恤",
    "seq": 151
  },
  {
    "assetbundleName": "avatar_costume_0052",
    "id": 152,
    "name": "1st Anniversary T恤",
    "seq": 152
  },
  {
    "assetbundleName": "avatar_costume_0053",
    "id": 153,
    "name": "想收集徽章T恤",
    "seq": 153
  },
  {
    "assetbundleName": "avatar_costume_0054",
    "id": 154,
    "name": "想收集壓克力鑰匙圈T恤",
    "seq": 154
  },
  {
    "assetbundleName": "avatar_costume_0055",
    "id": 155,
    "name": "RTVL白T恤",
    "seq": 155
  },
  {
    "assetbundleName": "avatar_costume_0056",
    "id": 156,
    "name": "RTVL黑T恤",
    "seq": 156
  },
  {
    "assetbundleName": "avatar_costume_0057",
    "id": 157,
    "name": "超喜歡咖喱飯T恤",
    "seq": 157
  },
  {
    "assetbundleName": "avatar_costume_0058",
    "id": 158,
    "name": "超喜歡炸薯條T恤",
    "seq": 158
  },
  {
    "assetbundleName": "avatar_costume_0059",
    "id": 159,
    "name": "超喜歡雪T恤",
    "seq": 159
  },
  {
    "assetbundleName": "avatar_costume_0060",
    "id": 160,
    "name": "超喜歡燈海T恤",
    "seq": 160
  },
  {
    "assetbundleName": "avatar_costume_0061",
    "id": 161,
    "name": "來玩歌牌T恤",
    "seq": 161
  },
  {
    "assetbundleName": "avatar_costume_0062",
    "id": 162,
    "name": "來玩笑福面T恤",
    "seq": 162
  },
  {
    "assetbundleName": "avatar_costume_0063",
    "id": 163,
    "name": "想要給情人節巧克力T恤",
    "seq": 163
  },
  {
    "assetbundleName": "avatar_costume_0064",
    "id": 164,
    "name": "想要得到情人節巧克力T恤",
    "seq": 164
  },
  {
    "assetbundleName": "avatar_costume_0065",
    "id": 165,
    "name": "超喜歡黑巧克力T恤",
    "seq": 165
  },
  {
    "assetbundleName": "avatar_costume_0066",
    "id": 166,
    "name": "超喜歡牛奶巧克力T恤",
    "seq": 166
  },
  {
    "assetbundleName": "avatar_costume_0067",
    "id": 167,
    "name": "想喝櫻花拿鐵T恤",
    "seq": 167
  },
  {
    "assetbundleName": "avatar_costume_0068",
    "id": 168,
    "name": "想喝櫻花奶昔T恤",
    "seq": 168
  },
  {
    "assetbundleName": "avatar_costume_0069",
    "id": 169,
    "name": "想聽炒熱氣氛的歌T恤",
    "seq": 169
  },
  {
    "assetbundleName": "avatar_costume_0070",
    "id": 170,
    "name": "想聽慢歌T恤",
    "seq": 170
  },
  {
    "assetbundleName": "avatar_costume_0071",
    "id": 171,
    "name": "教堂婚禮派T恤",
    "seq": 171
  },
  {
    "assetbundleName": "avatar_costume_0072",
    "id": 172,
    "name": "花園婚禮派T恤",
    "seq": 172
  },
  {
    "assetbundleName": "avatar_costume_0073",
    "id": 173,
    "name": "打棒球T恤",
    "seq": 173
  },
  {
    "assetbundleName": "avatar_costume_0074",
    "id": 174,
    "name": "踢足球T恤",
    "seq": 174
  },
  {
    "assetbundleName": "avatar_costume_0075",
    "id": 175,
    "name": "想要消除綠色氣泡T恤",
    "seq": 175
  },
  {
    "assetbundleName": "avatar_costume_0076",
    "id": 176,
    "name": "想要消除妨礙氣泡T恤",
    "seq": 176
  },
  {
    "assetbundleName": "avatar_costume_0077",
    "id": 177,
    "name": "想吃豚骨拉麵T恤",
    "seq": 177
  },
  {
    "assetbundleName": "avatar_costume_0078",
    "id": 178,
    "name": "想吃醬油拉麵T恤",
    "seq": 178
  },
  {
    "assetbundleName": "avatar_costume_0079",
    "id": 179,
    "name": "「JP 2nd ANNIVERSARY SPECIAL STAGE」SPECIAL LIVE T恤",
    "seq": 179
  },
  {
    "assetbundleName": "avatar_costume_0080",
    "id": 180,
    "name": "「JP 2nd ANNIVERSARY SPECIAL STAGE」LIVE T恤（白）",
    "seq": 180
  },
  {
    "assetbundleName": "avatar_costume_0081",
    "id": 181,
    "name": "「JP 2nd ANNIVERSARY SPECIAL STAGE」LIVE T恤（黑）",
    "seq": 181
  },
  {
    "assetbundleName": "avatar_costume_0082",
    "id": 182,
    "name": "想吃蘋果糖T恤",
    "seq": 182
  },
  {
    "assetbundleName": "avatar_costume_0083",
    "id": 183,
    "name": "想吃棉花糖T恤",
    "seq": 183
  },
  {
    "assetbundleName": "avatar_costume_0084",
    "id": 184,
    "name": "想在校慶開咖啡廳T恤",
    "seq": 184
  },
  {
    "assetbundleName": "avatar_costume_0085",
    "id": 185,
    "name": "想在校慶做鬼屋T恤",
    "seq": 185
  },
  {
    "assetbundleName": "avatar_costume_0086",
    "id": 186,
    "name": "經常看電視節目T恤",
    "seq": 186
  },
  {
    "assetbundleName": "avatar_costume_0087",
    "id": 187,
    "name": "經查看網路直播T恤",
    "seq": 187
  },
  {
    "assetbundleName": "avatar_costume_0088",
    "id": 188,
    "name": "想在山上看第一個日出T恤",
    "seq": 188
  },
  {
    "assetbundleName": "avatar_costume_0089",
    "id": 189,
    "name": "想在海邊看第一個日出T恤",
    "seq": 189
  },
  {
    "assetbundleName": "avatar_costume_0090",
    "id": 190,
    "name": "最喜歡柑橘類香氣T恤",
    "seq": 190
  },
  {
    "assetbundleName": "avatar_costume_0091",
    "id": 191,
    "name": "最喜歡鮮花類香氣T恤",
    "seq": 191
  },
  {
    "assetbundleName": "avatar_costume_0092",
    "id": 192,
    "name": "最喜歡咖啡T恤",
    "seq": 192
  },
  {
    "assetbundleName": "avatar_costume_0093",
    "id": 193,
    "name": "最喜歡紅茶T恤",
    "seq": 193
  },
  {
    "assetbundleName": "avatar_costume_0094",
    "id": 194,
    "name": "最喜歡金魚T恤",
    "seq": 194
  },
  {
    "assetbundleName": "avatar_costume_0095",
    "id": 195,
    "name": "最喜歡孔雀魚T恤",
    "seq": 195
  },
  {
    "assetbundleName": "avatar_costume_0096",
    "id": 196,
    "name": "「JUMPIN！」LIVE T恤（白）",
    "seq": 196
  },
  {
    "assetbundleName": "avatar_costume_0097",
    "id": 197,
    "name": "「JUMPIN！」LIVE T恤（黑）",
    "seq": 197
  },
  {
    "assetbundleName": "avatar_costume_0098",
    "id": 198,
    "name": "「SPARKLE」LIVE T恤（白）",
    "seq": 200
  },
  {
    "assetbundleName": "avatar_costume_0099",
    "id": 199,
    "name": "「SPARKLE」LIVE T恤（黑）",
    "seq": 201
  },
  {
    "assetbundleName": "avatar_costume_0100",
    "id": 200,
    "name": "想去平價餐廳T恤",
    "seq": 198
  },
  {
    "assetbundleName": "avatar_costume_0101",
    "id": 201,
    "name": "想去卡拉ok T恤",
    "seq": 199
  },
  {
    "assetbundleName": "avatar_costume_0102",
    "id": 202,
    "name": "最喜歡切蛋糕T恤",
    "seq": 202
  },
  {
    "assetbundleName": "avatar_costume_0103",
    "id": 203,
    "name": "最喜歡丟捧花T恤",
    "seq": 203
  },
  {
    "assetbundleName": "avatar_costume_0104",
    "id": 204,
    "name": "想要體驗做日式點心T恤",
    "seq": 204
  },
  {
    "assetbundleName": "avatar_costume_0105",
    "id": 205,
    "name": "想要體驗茶道T恤",
    "seq": 205
  },
  {
    "assetbundleName": "avatar_costume_0106",
    "id": 206,
    "name": "「moment」LIVE T恤（白）",
    "seq": 206
  },
  {
    "assetbundleName": "avatar_costume_0107",
    "id": 207,
    "name": "「moment」LIVE T恤（黑）",
    "seq": 207
  },
  {
    "assetbundleName": "avatar_costume_0108",
    "id": 208,
    "name": "「STORIES」LIVE T恤（白）",
    "seq": 208
  },
  {
    "assetbundleName": "avatar_costume_0109",
    "id": 209,
    "name": "「STORIES」LIVE T恤（黑）",
    "seq": 209
  },
  {
    "assetbundleName": "avatar_costume_0110",
    "id": 210,
    "name": "想吃草莓聖代T恤",
    "seq": 210
  },
  {
    "assetbundleName": "avatar_costume_0111",
    "id": 211,
    "name": "想吃布丁聖代T恤",
    "seq": 211
  },
  {
    "assetbundleName": "avatar_costume_0112",
    "id": 212,
    "name": "想用唱歌支持T恤",
    "seq": 214
  },
  {
    "assetbundleName": "avatar_costume_0113",
    "id": 213,
    "name": "想用演奏支持T恤",
    "seq": 215
  },
  {
    "assetbundleName": "avatar_costume_0114",
    "id": 214,
    "name": "想加入廣播股長會T恤",
    "seq": 216
  },
  {
    "assetbundleName": "avatar_costume_0115",
    "id": 215,
    "name": "想加入飼育股長T恤",
    "seq": 217
  },
  {
    "assetbundleName": "avatar_costume_0118",
    "id": 216,
    "name": "「3rd ANNIVERSARY Memorial Stage」特別LIVE T恤",
    "seq": 218
  },
  {
    "assetbundleName": "avatar_costume_0116",
    "id": 217,
    "name": "「3rd ANNIVERSARY Memorial Stage」LIVE T恤(白)",
    "seq": 219
  },
  {
    "assetbundleName": "avatar_costume_0117",
    "id": 218,
    "name": "「3rd ANNIVERSARY Memorial Stage」LIVE T恤(黑)",
    "seq": 220
  },
  {
    "assetbundleName": "avatar_costume_0119",
    "id": 219,
    "name": "sekaiuniform",
    "seq": 212
  },
  {
    "assetbundleName": "avatar_costume_0120",
    "id": 220,
    "name": "工作人員",
    "seq": 213
  },
  {
    "assetbundleName": "avatar_costume_0121",
    "id": 221,
    "name": "想吃溫泉饅頭T恤",
    "seq": 221
  },
  {
    "assetbundleName": "avatar_costume_0122",
    "id": 222,
    "name": "想吃溫泉蛋T恤",
    "seq": 222
  },
  {
    "assetbundleName": "avatar_costume_0123",
    "id": 223,
    "name": "想看動作片T恤",
    "seq": 223
  },
  {
    "assetbundleName": "avatar_costume_0124",
    "id": 224,
    "name": "想看搞笑片T恤",
    "seq": 224
  },
  {
    "assetbundleName": "avatar_costume_0125",
    "id": 225,
    "name": "想吃年糕湯T恤",
    "seq": 225
  },
  {
    "assetbundleName": "avatar_costume_0126",
    "id": 226,
    "name": "想吃年菜T恤",
    "seq": 226
  },
  {
    "assetbundleName": "avatar_costume_0127",
    "id": 227,
    "name": "想用相機拍照T恤",
    "seq": 227
  },
  {
    "assetbundleName": "avatar_costume_0128",
    "id": 228,
    "name": "想用智慧型手機拍照T恤",
    "seq": 228
  },
  {
    "assetbundleName": "avatar_costume_0129",
    "id": 229,
    "name": "想喝花草茶T恤",
    "seq": 229
  },
  {
    "assetbundleName": "avatar_costume_0130",
    "id": 230,
    "name": "想喝薑茶T恤",
    "seq": 230
  },
  {
    "assetbundleName": "avatar_costume_0131",
    "id": 231,
    "name": "想玩飛盤T恤",
    "seq": 231
  },
  {
    "assetbundleName": "avatar_costume_0132",
    "id": 232,
    "name": "想散步T恤",
    "seq": 232
  },
  {
    "assetbundleName": "avatar_costume_0133",
    "id": 233,
    "name": "「RESONANCE BEATS!!」LIVE T恤（白）",
    "seq": 235
  },
  {
    "assetbundleName": "avatar_costume_0134",
    "id": 234,
    "name": "「RESONANCE BEATS!!」LIVE T恤（黑）",
    "seq": 236
  },
  {
    "assetbundleName": "avatar_costume_0137",
    "id": 237,
    "name": "「RESONANCE BEATS!!」特別LIVE T恤",
    "seq": 237
  },
  {
    "assetbundleName": "avatar_costume_0138",
    "id": 238,
    "name": "想在水族館看看結婚典禮T恤",
    "seq": 233
  },
  {
    "assetbundleName": "avatar_costume_0139",
    "id": 239,
    "name": "想在模擬天文館看看結婚典禮T恤",
    "seq": 234
  },
  {
    "assetbundleName": "avatar_costume_0142",
    "id": 242,
    "name": "「4th ANNIVERSARY Brilliant Stage」特別LIVE T恤",
    "seq": 242
  },
  {
    "assetbundleName": "avatar_costume_0143",
    "id": 243,
    "name": "「4th ANNIVERSARY Brilliant Stage」LIVE T恤（白）",
    "seq": 243
  },
  {
    "assetbundleName": "avatar_costume_0144",
    "id": 244,
    "name": "「4th ANNIVERSARY Brilliant Stage」LIVE T恤（黑）",
    "seq": 244
  },
  {
    "assetbundleName": "avatar_costume_0145",
    "id": 245,
    "name": "ES偶像服裝",
    "seq": 245
  },
  {
    "assetbundleName": "avatar_costume_0146",
    "id": 246,
    "name": "「Ensemble in SEKAI」特別LIVE T恤",
    "seq": 246
  },
  {
    "assetbundleName": "avatar_costume_0147",
    "id": 247,
    "name": "「Ensemble in SEKAI」LIVE T恤（白）",
    "seq": 247
  },
  {
    "assetbundleName": "avatar_costume_0148",
    "id": 248,
    "name": "「Ensemble in SEKAI」LIVE T恤（黑）",
    "seq": 248
  },
  {
    "assetbundleName": "avatar_costume_0149",
    "id": 249,
    "name": "姓氏T恤「近藤」",
    "seq": 249
  },
  {
    "assetbundleName": "avatar_costume_0150",
    "id": 250,
    "name": "姓氏T恤「安達」",
    "seq": 250
  },
  {
    "assetbundleName": "avatar_costume_0151",
    "id": 251,
    "name": "「Dreamscape」LIVE T恤（白）",
    "seq": 251
  },
  {
    "assetbundleName": "avatar_costume_0152",
    "id": 252,
    "name": "「Dreamscape」LIVE T恤（黑）",
    "seq": 252
  },
  {
    "assetbundleName": "avatar_costume_0153",
    "id": 253,
    "name": "「Dreamscape」特別LIVE T恤",
    "seq": 253
  }
]