[
  {
    "canUse": false,
    "flavorText": "解鎖卡片劇情或交換區域道具所需的道具。\n透過LIVE等方式取得。",
    "id": 1,
    "materialType": "common",
    "name": "可愛碎片",
    "seq": 10001
  },
  {
    "canUse": false,
    "flavorText": "解鎖卡片劇情或交換區域道具所需的道具。\n透過LIVE等方式取得。",
    "id": 2,
    "materialType": "common",
    "name": "帥氣碎片",
    "seq": 10002
  },
  {
    "canUse": false,
    "flavorText": "解鎖卡片劇情或交換區域道具所需的道具。\n透過LIVE等方式取得。",
    "id": 3,
    "materialType": "common",
    "name": "純真碎片",
    "seq": 10003
  },
  {
    "canUse": false,
    "flavorText": "解鎖卡片劇情或交換區域道具所需的道具。\n透過LIVE等方式取得。",
    "id": 4,
    "materialType": "common",
    "name": "快樂碎片",
    "seq": 10004
  },
  {
    "canUse": false,
    "flavorText": "解鎖卡片劇情或交換區域道具所需的道具。\n透過LIVE等方式取得。",
    "id": 5,
    "materialType": "common",
    "name": "神秘碎片",
    "seq": 10005
  },
  {
    "canUse": false,
    "flavorText": "解鎖卡片劇情或交換區域道具所需的道具。\n透過LIVE等方式取得。",
    "id": 6,
    "materialType": "common",
    "name": "可愛寶石",
    "seq": 10006
  },
  {
    "canUse": false,
    "flavorText": "解鎖卡片劇情或交換區域道具所需的道具。\n透過LIVE等方式取得。",
    "id": 7,
    "materialType": "common",
    "name": "帥氣寶石",
    "seq": 10007
  },
  {
    "canUse": false,
    "flavorText": "解鎖卡片劇情或交換區域道具所需的道具。\n透過LIVE等方式取得。",
    "id": 8,
    "materialType": "common",
    "name": "純真寶石",
    "seq": 10008
  },
  {
    "canUse": false,
    "flavorText": "解鎖卡片劇情或交換區域道具所需的道具。\n透過LIVE等方式取得。",
    "id": 9,
    "materialType": "common",
    "name": "快樂寶石",
    "seq": 10009
  },
  {
    "canUse": false,
    "flavorText": "解鎖卡片劇情或交換區域道具所需的道具。\n透過LIVE等方式取得。",
    "id": 10,
    "materialType": "common",
    "name": "神秘寶石",
    "seq": 10010
  },
  {
    "canUse": false,
    "flavorText": "製作服裝所需的道具。透過LIVE等方式取得。",
    "id": 11,
    "materialType": "costume",
    "name": "魔法布",
    "seq": 10011
  },
  {
    "canUse": false,
    "flavorText": "製作服裝所需的道具。透過LIVE等方式取得。",
    "id": 12,
    "materialType": "costume",
    "name": "魔法線",
    "seq": 10012
  },
  {
    "canUse": false,
    "flavorText": "可在唱片行交換歌曲。透過任務或劇情等方式取得。",
    "id": 13,
    "materialType": "music",
    "name": "音樂卡",
    "seq": 10013
  },
  {
    "canUse": false,
    "flavorText": "解鎖特訓或卡片劇情所需的道具。\n透過LIVE等方式取得。",
    "id": 14,
    "materialType": "special_training",
    "name": "奇蹟寶石",
    "seq": 10014
  },
  {
    "canUse": false,
    "flavorText": "技能升級所需的道具。\n在休息室中以★2、★3成員交換取得。",
    "id": 15,
    "materialType": "master_lesson",
    "name": "心願碎片",
    "seq": 10101
  },
  {
    "canUse": false,
    "flavorText": "技能升級所需的道具。\n在休息室中以★4成員交換取得。",
    "id": 16,
    "materialType": "master_lesson",
    "name": "心願純結晶",
    "seq": 10201
  },
  {
    "canUse": false,
    "flavorText": "送去園藝社可交換區域道具。\n透過LIVE等方式取得。",
    "id": 17,
    "materialType": "common",
    "name": "不可思議的種子",
    "seq": 10015
  },
  {
    "canUse": false,
    "flavorText": "可交換一歌的Another Vocal ver歌曲。\n透過角色等級報酬取得。",
    "id": 18,
    "materialType": "music",
    "name": "一歌的主唱卡",
    "seq": 10302
  },
  {
    "canUse": false,
    "flavorText": "可交換咲希的Another Vocal ver歌曲。\n透過角色等級報酬取得。",
    "id": 19,
    "materialType": "music",
    "name": "咲希的主唱卡",
    "seq": 10303
  },
  {
    "canUse": false,
    "flavorText": "可交換穗波的Another Vocal ver歌曲。\n透過角色等級報酬取得。",
    "id": 20,
    "materialType": "music",
    "name": "穗波的主唱卡",
    "seq": 10304
  },
  {
    "canUse": false,
    "flavorText": "可交換志步的Another Vocal ver歌曲。\n透過角色等級報酬取得。",
    "id": 21,
    "materialType": "music",
    "name": "志步的主唱卡",
    "seq": 10305
  },
  {
    "canUse": false,
    "flavorText": "可交換實乃理的Another Vocal ver歌曲。\n透過角色等級報酬取得。",
    "id": 22,
    "materialType": "music",
    "name": "實乃理的主唱卡",
    "seq": 10306
  },
  {
    "canUse": false,
    "flavorText": "可交換遙的Another Vocal ver歌曲。\n透過角色等級報酬取得。",
    "id": 23,
    "materialType": "music",
    "name": "遙的主唱卡",
    "seq": 10307
  },
  {
    "canUse": false,
    "flavorText": "可交換愛莉的Another Vocal ver歌曲。\n透過角色等級報酬取得。",
    "id": 24,
    "materialType": "music",
    "name": "愛莉的主唱卡",
    "seq": 10308
  },
  {
    "canUse": false,
    "flavorText": "可交換雫的Another Vocal ver歌曲。\n透過角色等級報酬取得。",
    "id": 25,
    "materialType": "music",
    "name": "雫的主唱卡",
    "seq": 10309
  },
  {
    "canUse": false,
    "flavorText": "可交換心羽的Another Vocal ver歌曲。\n透過角色等級報酬取得。",
    "id": 26,
    "materialType": "music",
    "name": "心羽的主唱卡",
    "seq": 10310
  },
  {
    "canUse": false,
    "flavorText": "可交換杏的Another Vocal ver歌曲。\n透過角色等級報酬取得。",
    "id": 27,
    "materialType": "music",
    "name": "杏的主唱卡",
    "seq": 10311
  },
  {
    "canUse": false,
    "flavorText": "可交換彰人的Another Vocal ver歌曲。\n透過角色等級報酬取得。",
    "id": 28,
    "materialType": "music",
    "name": "彰人的主唱卡",
    "seq": 10312
  },
  {
    "canUse": false,
    "flavorText": "可交換冬彌的Another Vocal ver歌曲。\n透過角色等級報酬取得。",
    "id": 29,
    "materialType": "music",
    "name": "冬彌的主唱卡",
    "seq": 10313
  },
  {
    "canUse": false,
    "flavorText": "可交換司的Another Vocal ver歌曲。\n透過角色等級報酬取得。",
    "id": 30,
    "materialType": "music",
    "name": "司的主唱卡",
    "seq": 10314
  },
  {
    "canUse": false,
    "flavorText": "可交換笑夢的Another Vocal ver歌曲。\n透過角色等級報酬取得。",
    "id": 31,
    "materialType": "music",
    "name": "笑夢的主唱卡",
    "seq": 10315
  },
  {
    "canUse": false,
    "flavorText": "可交換寧寧的Another Vocal ver歌曲。\n透過角色等級報酬取得。",
    "id": 32,
    "materialType": "music",
    "name": "寧寧的主唱卡",
    "seq": 10316
  },
  {
    "canUse": false,
    "flavorText": "可交換類的Another Vocal ver歌曲。\n透過角色等級報酬取得。",
    "id": 33,
    "materialType": "music",
    "name": "類的主唱卡",
    "seq": 10317
  },
  {
    "canUse": false,
    "flavorText": "可交換奏的Another Vocal ver歌曲。\n透過角色等級報酬取得。",
    "id": 34,
    "materialType": "music",
    "name": "奏的主唱卡",
    "seq": 10318
  },
  {
    "canUse": false,
    "flavorText": "可交換真冬的Another Vocal ver歌曲。\n透過角色等級報酬取得。",
    "id": 35,
    "materialType": "music",
    "name": "真冬的主唱卡",
    "seq": 10319
  },
  {
    "canUse": false,
    "flavorText": "可交換繪名的Another Vocal ver歌曲。\n透過角色等級報酬取得。",
    "id": 36,
    "materialType": "music",
    "name": "繪名的主唱卡",
    "seq": 10320
  },
  {
    "canUse": false,
    "flavorText": "可交換瑞希的Another Vocal ver歌曲。\n透過角色等級報酬取得。",
    "id": 37,
    "materialType": "music",
    "name": "瑞希的主唱卡",
    "seq": 10321
  },
  {
    "canUse": false,
    "flavorText": "可交換初音未來的Another Vocal ver歌曲。\n透過角色等級報酬取得。",
    "id": 38,
    "materialType": "music",
    "name": "初音未來的主唱卡",
    "seq": 10322
  },
  {
    "canUse": false,
    "flavorText": "可交換鏡音鈴的Another Vocal ver歌曲。\n透過角色等級報酬取得。",
    "id": 39,
    "materialType": "music",
    "name": "鏡音鈴的主唱卡",
    "seq": 10323
  },
  {
    "canUse": false,
    "flavorText": "可交換鏡音連的Another Vocal ver歌曲。\n透過角色等級報酬取得。",
    "id": 40,
    "materialType": "music",
    "name": "鏡音連的主唱卡",
    "seq": 10324
  },
  {
    "canUse": false,
    "flavorText": "可交換巡音流歌的Another Vocal ver歌曲。\n透過角色等級報酬取得。",
    "id": 41,
    "materialType": "music",
    "name": "巡音流歌的主唱卡",
    "seq": 10325
  },
  {
    "canUse": false,
    "flavorText": "可交換MEIKO的Another Vocal ver歌曲。\n透過角色等級報酬取得。",
    "id": 42,
    "materialType": "music",
    "name": "MEIKO的主唱卡",
    "seq": 10326
  },
  {
    "canUse": false,
    "flavorText": "可交換KAITO的Another Vocal ver歌曲。\n透過角色等級報酬取得。",
    "id": 43,
    "materialType": "music",
    "name": "KAITO的主唱卡",
    "seq": 10327
  },
  {
    "canUse": false,
    "flavorText": "可在貼圖商店交換貼圖。\n透過角色等級報酬等方式取得。",
    "id": 44,
    "materialType": "common",
    "name": "貼圖交換券",
    "seq": 10015
  },
  {
    "canUse": false,
    "flavorText": "可在★3票券交換所交換喜歡的★3成員。",
    "id": 45,
    "materialType": "card_ticket",
    "name": "★3成員選擇券",
    "seq": 45
  },
  {
    "canUse": false,
    "flavorText": "可在★4票券交換所交換喜歡的★4成員。",
    "id": 46,
    "materialType": "card_ticket",
    "name": "★4成員選擇券",
    "seq": 46
  },
  {
    "canUse": false,
    "flavorText": "可以配合一般招募貼紙，交換常駐成員。",
    "id": 47,
    "materialType": "gacha_ceil_ticket",
    "name": "招募貼紙交換券",
    "seq": 10501
  },
  {
    "canUse": false,
    "flavorText": "可以配合限定招募貼紙，\n交換期間限定、七彩限定、常駐成員。",
    "id": 48,
    "materialType": "gacha_ceil_ticket",
    "name": "限定招募貼紙交換券",
    "seq": 10502
  },
  {
    "canUse": false,
    "flavorText": "可在主唱卡交換所中，交換任意角色的主唱卡。",
    "id": 49,
    "materialType": "vocal_card_ticket",
    "name": "主唱卡交換券",
    "seq": 10301
  },
  {
    "canUse": false,
    "flavorText": "可在主唱卡交換所中，交換對象團體角色的主唱卡。",
    "id": 50,
    "materialType": "vocal_card_ticket",
    "name": "Leo/need\n 主唱卡交換券",
    "seq": 10328
  },
  {
    "canUse": false,
    "flavorText": "可在主唱卡交換所中，交換對象團體角色的主唱卡。",
    "id": 51,
    "materialType": "vocal_card_ticket",
    "name": "MORE MORE JUMP！\n 主唱卡交換券",
    "seq": 10329
  },
  {
    "canUse": false,
    "flavorText": "可在主唱卡交換所中，交換對象團體角色的主唱卡。",
    "id": 52,
    "materialType": "vocal_card_ticket",
    "name": "Vivid BAD SQUAD\n 主唱卡交換券",
    "seq": 10330
  },
  {
    "canUse": false,
    "flavorText": "可在主唱卡交換所中，交換對象團體角色的主唱卡。",
    "id": 53,
    "materialType": "vocal_card_ticket",
    "name": "Wonderlands×Showtime\n 主唱卡交換券",
    "seq": 10331
  },
  {
    "canUse": false,
    "flavorText": "可在主唱卡交換所中，交換對象團體角色的主唱卡。",
    "id": 54,
    "materialType": "vocal_card_ticket",
    "name": "25點，Nightcord見。\n 主唱卡交換券",
    "seq": 10332
  },
  {
    "canUse": false,
    "flavorText": "[新手限定]可在★4成員交換所中，交換★4成員。",
    "id": 55,
    "materialType": "card_ticket",
    "name": "新手限定選擇券",
    "seq": 55
  },
  {
    "canUse": false,
    "flavorText": "[新春2022]可在★3成員交換所中，交換★3成員。",
    "id": 56,
    "materialType": "card_ticket",
    "name": "[新春2022]★3成員選擇券",
    "seq": 56
  },
  {
    "canUse": false,
    "flavorText": "將區域道具提升到特定等級的必備道具。",
    "id": 57,
    "materialType": "common",
    "name": "祈願水滴",
    "seq": 10016
  },
  {
    "canUse": false,
    "flavorText": "可在★4票券交換所交換喜歡的★4成員。",
    "id": 58,
    "materialType": "card_ticket",
    "name": "★4成員選擇券",
    "seq": 57
  },
  {
    "canUse": false,
    "flavorText": "可在★4票券交換所交換喜歡的★4成員。",
    "id": 59,
    "materialType": "card_ticket",
    "name": "★4成員選擇券",
    "seq": 58
  },
  {
    "canUse": true,
    "changeFlavorTextAt": 1743249600000,
    "flavorText": "裝滿一歌心願的小瓶子。\n可能總有一天能在「世界」中使用。",
    "flavorText2": "裝滿一歌心願的小瓶子。\n可獲得一歌的1角色EXP。",
    "id": 60,
    "materialType": "character_rank_exp_ticket",
    "name": "一歌的心願小瓶子",
    "seq": 10401
  },
  {
    "canUse": true,
    "changeFlavorTextAt": 1743249600000,
    "flavorText": "裝滿咲希心願的小瓶子。\n可能總有一天能在「世界」中使用。",
    "flavorText2": "裝滿咲希心願的小瓶子。\n可獲得咲希的1角色EXP。",
    "id": 61,
    "materialType": "character_rank_exp_ticket",
    "name": "咲希的心願小瓶子",
    "seq": 10402
  },
  {
    "canUse": true,
    "changeFlavorTextAt": 1743249600000,
    "flavorText": "裝滿穗波心願的小瓶子。\n可能總有一天能在「世界」中使用。",
    "flavorText2": "裝滿穗波心願的小瓶子。\n可獲得穗波的1角色EXP。",
    "id": 62,
    "materialType": "character_rank_exp_ticket",
    "name": "穗波的心願小瓶子",
    "seq": 10403
  },
  {
    "canUse": true,
    "changeFlavorTextAt": 1743249600000,
    "flavorText": "裝滿志步心願的小瓶子。\n可能總有一天能在「世界」中使用。",
    "flavorText2": "裝滿志步心願的小瓶子。\n可獲得志步的1角色EXP。",
    "id": 63,
    "materialType": "character_rank_exp_ticket",
    "name": "志步的心願小瓶子",
    "seq": 10404
  },
  {
    "canUse": true,
    "changeFlavorTextAt": 1743249600000,
    "flavorText": "裝滿實乃理心願的小瓶子。\n可能總有一天能在「世界」中使用。",
    "flavorText2": "裝滿實乃理心願的小瓶子。\n可獲得實乃理的1角色EXP。",
    "id": 64,
    "materialType": "character_rank_exp_ticket",
    "name": "實乃理的心願小瓶子",
    "seq": 10405
  },
  {
    "canUse": true,
    "changeFlavorTextAt": 1743249600000,
    "flavorText": "裝滿遙心願的小瓶子。\n可能總有一天能在「世界」中使用。",
    "flavorText2": "裝滿遙心願的小瓶子。\n可獲得遙的1角色EXP。",
    "id": 65,
    "materialType": "character_rank_exp_ticket",
    "name": "遙的心願小瓶子",
    "seq": 10406
  },
  {
    "canUse": true,
    "changeFlavorTextAt": 1743249600000,
    "flavorText": "裝滿愛莉心願的小瓶子。\n可能總有一天能在「世界」中使用。",
    "flavorText2": "裝滿愛莉心願的小瓶子。\n可獲得愛莉的1角色EXP。",
    "id": 66,
    "materialType": "character_rank_exp_ticket",
    "name": "愛莉的心願小瓶子",
    "seq": 10407
  },
  {
    "canUse": true,
    "changeFlavorTextAt": 1743249600000,
    "flavorText": "裝滿雫心願的小瓶子。\n可能總有一天能在「世界」中使用。",
    "flavorText2": "裝滿雫心願的小瓶子。\n可獲得雫的1角色EXP。",
    "id": 67,
    "materialType": "character_rank_exp_ticket",
    "name": "雫的心願小瓶子",
    "seq": 10408
  },
  {
    "canUse": true,
    "changeFlavorTextAt": 1743249600000,
    "flavorText": "裝滿心羽心願的小瓶子。\n可能總有一天能在「世界」中使用。",
    "flavorText2": "裝滿心羽心願的小瓶子。\n可獲得心羽的1角色EXP。",
    "id": 68,
    "materialType": "character_rank_exp_ticket",
    "name": "心羽的心願小瓶子",
    "seq": 10409
  },
  {
    "canUse": true,
    "changeFlavorTextAt": 1743249600000,
    "flavorText": "裝滿杏心願的小瓶子。\n可能總有一天能在「世界」中使用。",
    "flavorText2": "裝滿杏心願的小瓶子。\n可獲得杏的1角色EXP。",
    "id": 69,
    "materialType": "character_rank_exp_ticket",
    "name": "杏的心願小瓶子",
    "seq": 10410
  },
  {
    "canUse": true,
    "changeFlavorTextAt": 1743249600000,
    "flavorText": "裝滿彰人心願的小瓶子。\n可能總有一天能在「世界」中使用。",
    "flavorText2": "裝滿彰人心願的小瓶子。\n可獲得彰人的1角色EXP。",
    "id": 70,
    "materialType": "character_rank_exp_ticket",
    "name": "彰人的心願小瓶子",
    "seq": 10411
  },
  {
    "canUse": true,
    "changeFlavorTextAt": 1743249600000,
    "flavorText": "裝滿冬彌心願的小瓶子。\n可能總有一天能在「世界」中使用。",
    "flavorText2": "裝滿冬彌心願的小瓶子。\n可獲得冬彌的1角色EXP。",
    "id": 71,
    "materialType": "character_rank_exp_ticket",
    "name": "冬彌的心願小瓶子",
    "seq": 10412
  },
  {
    "canUse": true,
    "changeFlavorTextAt": 1743249600000,
    "flavorText": "裝滿司心願的小瓶子。\n可能總有一天能在「世界」中使用。",
    "flavorText2": "裝滿司心願的小瓶子。\n可獲得司的1角色EXP。",
    "id": 72,
    "materialType": "character_rank_exp_ticket",
    "name": "司的心願小瓶子",
    "seq": 10413
  },
  {
    "canUse": true,
    "changeFlavorTextAt": 1743249600000,
    "flavorText": "裝滿笑夢心願的小瓶子。\n可能總有一天能在「世界」中使用。",
    "flavorText2": "裝滿笑夢心願的小瓶子。\n可獲得笑夢的1角色EXP。",
    "id": 73,
    "materialType": "character_rank_exp_ticket",
    "name": "笑夢的心願小瓶子",
    "seq": 10414
  },
  {
    "canUse": true,
    "changeFlavorTextAt": 1743249600000,
    "flavorText": "裝滿寧寧心願的小瓶子。\n可能總有一天能在「世界」中使用。",
    "flavorText2": "裝滿寧寧心願的小瓶子。\n可獲得寧寧的1角色EXP。",
    "id": 74,
    "materialType": "character_rank_exp_ticket",
    "name": "寧寧的心願小瓶子",
    "seq": 10415
  },
  {
    "canUse": true,
    "changeFlavorTextAt": 1743249600000,
    "flavorText": "裝滿類心願的小瓶子。\n可能總有一天能在「世界」中使用。",
    "flavorText2": "裝滿類心願的小瓶子。\n可獲得類的1角色EXP。",
    "id": 75,
    "materialType": "character_rank_exp_ticket",
    "name": "類的心願小瓶子",
    "seq": 10416
  },
  {
    "canUse": true,
    "changeFlavorTextAt": 1743249600000,
    "flavorText": "裝滿奏心願的小瓶子。\n可能總有一天能在「世界」中使用。",
    "flavorText2": "裝滿奏心願的小瓶子。\n可獲得奏的1角色EXP。",
    "id": 76,
    "materialType": "character_rank_exp_ticket",
    "name": "奏的心願小瓶子",
    "seq": 10417
  },
  {
    "canUse": true,
    "changeFlavorTextAt": 1743249600000,
    "flavorText": "裝滿真冬心願的小瓶子。\n可能總有一天能在「世界」中使用。",
    "flavorText2": "裝滿真冬心願的小瓶子。\n可獲得真冬的1角色EXP。",
    "id": 77,
    "materialType": "character_rank_exp_ticket",
    "name": "真冬的心願小瓶子",
    "seq": 10418
  },
  {
    "canUse": true,
    "changeFlavorTextAt": 1743249600000,
    "flavorText": "裝滿繪名心願的小瓶子。\n可能總有一天能在「世界」中使用。",
    "flavorText2": "裝滿繪名心願的小瓶子。\n可獲得繪名的1角色EXP。",
    "id": 78,
    "materialType": "character_rank_exp_ticket",
    "name": "繪名的心願小瓶子",
    "seq": 10419
  },
  {
    "canUse": true,
    "changeFlavorTextAt": 1743249600000,
    "flavorText": "裝滿瑞希心願的小瓶子。\n可能總有一天能在「世界」中使用。",
    "flavorText2": "裝滿瑞希心願的小瓶子。\n可獲得瑞希的1角色EXP。",
    "id": 79,
    "materialType": "character_rank_exp_ticket",
    "name": "瑞希的心願小瓶子",
    "seq": 10420
  },
  {
    "canUse": true,
    "changeFlavorTextAt": 1743249600000,
    "flavorText": "裝滿初音未來心願的小瓶子。\n可能總有一天能在「世界」中使用。",
    "flavorText2": "裝滿未來心願的小瓶子。\n可獲得未來的1角色EXP。",
    "id": 80,
    "materialType": "character_rank_exp_ticket",
    "name": "初音未來的心願小瓶子",
    "seq": 10421
  },
  {
    "canUse": true,
    "changeFlavorTextAt": 1743249600000,
    "flavorText": "裝滿鏡音鈴心願的小瓶子。\n可能總有一天能在「世界」中使用。",
    "flavorText2": "裝滿鈴心願的小瓶子。\n可獲得鈴的1角色EXP。",
    "id": 81,
    "materialType": "character_rank_exp_ticket",
    "name": "鏡音鈴的心願小瓶子",
    "seq": 10422
  },
  {
    "canUse": true,
    "changeFlavorTextAt": 1743249600000,
    "flavorText": "裝滿鏡音連心願的小瓶子。\n可能總有一天能在「世界」中使用。",
    "flavorText2": "裝滿連心願的小瓶子。\n可獲得連的1角色EXP。",
    "id": 82,
    "materialType": "character_rank_exp_ticket",
    "name": "鏡音連的心願小瓶子",
    "seq": 10423
  },
  {
    "canUse": true,
    "changeFlavorTextAt": 1743249600000,
    "flavorText": "裝滿巡音流歌心願的小瓶子。\n可能總有一天能在「世界」中使用。",
    "flavorText2": "裝滿流歌心願的小瓶子。\n可獲得流歌的1角色EXP。",
    "id": 83,
    "materialType": "character_rank_exp_ticket",
    "name": "巡音流歌的心願小瓶子",
    "seq": 10424
  },
  {
    "canUse": true,
    "changeFlavorTextAt": 1743249600000,
    "flavorText": "裝滿MEIKO心願的小瓶子。\n可能總有一天能在「世界」中使用。",
    "flavorText2": "裝滿MEIKO心願的小瓶子。\n可獲得MEIKO的1角色EXP。",
    "id": 84,
    "materialType": "character_rank_exp_ticket",
    "name": "MEIKO的心願小瓶子",
    "seq": 10425
  },
  {
    "canUse": true,
    "changeFlavorTextAt": 1743249600000,
    "flavorText": "裝滿KAITO心願的小瓶子。\n可能總有一天能在「世界」中使用。",
    "flavorText2": "裝滿KAITO心願的小瓶子。\n可獲得KAITO的1角色EXP。",
    "id": 85,
    "materialType": "character_rank_exp_ticket",
    "name": "KAITO的心願小瓶子",
    "seq": 10426
  },
  {
    "canUse": false,
    "flavorText": "在解鎖卡片劇情時，可代替碎片、寶石做使用的票券。可透過水晶商店獲得。",
    "id": 86,
    "materialType": "card_episode_release_ticket",
    "name": "卡片劇情票券",
    "seq": 10017
  },
  {
    "canUse": false,
    "flavorText": "可至3900's交換所交換報酬。\n使用期限：2024/05/14 23:59",
    "id": 87,
    "materialType": "common",
    "name": "3900's 票券",
    "seq": 10601
  },
  {
    "canUse": false,
    "flavorText": "可兌換在「連線LIVE Leo/need × Vivid BAD SQUAD RESONANCE BEATS!!」公演中發表之歌曲的連線LIVE ver. Vocal。",
    "id": 88,
    "materialType": "auto_exchange_music_vocal_ticket",
    "name": "「連線LIVE RESONANCE BEATS!!」連線LIVE ver. Vocal兌換卡",
    "seq": 20001
  },
  {
    "canUse": false,
    "flavorText": "因虛擬歌手們的心願而盛開的花朵花瓣。可使用於幸運之花遊行交換所。\n使用期限：2025/11/14 23:59",
    "id": 89,
    "materialType": "common",
    "name": "白色花瓣",
    "seq": 10602
  },
  {
    "canUse": false,
    "flavorText": "因Leo/need全體成員的心願而盛開的花朵花瓣。可使用於幸運之花遊行交換所。\n使用期限：2025/11/14 23:59",
    "id": 90,
    "materialType": "common",
    "name": "藍色花瓣",
    "seq": 10603
  },
  {
    "canUse": false,
    "flavorText": "因MORE MORE JUMP！全體成員的心願而盛開的花朵花瓣。可使用於幸運之花遊行交換所。\n使用期限：2025/11/14 23:59",
    "id": 91,
    "materialType": "common",
    "name": "綠色花瓣",
    "seq": 10604
  },
  {
    "canUse": false,
    "flavorText": "因Vivid BAD SQUAD全體成員的心願而盛開的花朵花瓣。可使用於幸運之花遊行交換所。\n使用期限：2025/11/14 23:59",
    "id": 92,
    "materialType": "common",
    "name": "紅色花瓣",
    "seq": 10605
  },
  {
    "canUse": false,
    "flavorText": "因Wonderlands×Showtime全體成員的心願而盛開的花朵花瓣。可使用於幸運之花遊行交換所。\n使用期限：2025/11/14 23:59",
    "id": 93,
    "materialType": "common",
    "name": "橘色花瓣",
    "seq": 10606
  },
  {
    "canUse": false,
    "flavorText": "因25點，Nightcord見。全體成員的心願而盛開的花朵花瓣。可使用於幸運之花遊行交換所。\n使用期限：2025/11/14 23:59",
    "id": 94,
    "materialType": "common",
    "name": "紫色花瓣",
    "seq": 10607
  },
  {
    "canUse": false,
    "flavorText": "因虛擬歌手全體成員的心願而盛開的花朵花瓣。可使用於幸運之花遊行交換所。\n使用期限：2025/11/14 23:59",
    "id": 95,
    "materialType": "common",
    "name": "白色幸運之花",
    "seq": 10608
  },
  {
    "canUse": false,
    "flavorText": "因Leo/need全體成員的心願而盛開的花朵。可使用於幸運之花遊行交換所。\n使用期限：2025/11/14 23:59",
    "id": 96,
    "materialType": "common",
    "name": "藍色幸運之花",
    "seq": 10609
  },
  {
    "canUse": false,
    "flavorText": "因MORE MORE JUMP！全體成員的心願而盛開的花朵。可使用於幸運之花遊行交換所。\n使用期限：2025/11/14 23:59",
    "id": 97,
    "materialType": "common",
    "name": "綠色幸運之花",
    "seq": 10610
  },
  {
    "canUse": false,
    "flavorText": "因Vivid BAD SQUAD全體成員的心願而盛開的花朵。可使用於幸運之花遊行交換所。\n使用期限：2025/11/14 23:59",
    "id": 98,
    "materialType": "common",
    "name": "紅色幸運之花",
    "seq": 10611
  },
  {
    "canUse": false,
    "flavorText": "因Wonderlands×Showtime全體成員的心願而盛開的花朵。可使用於幸運之花遊行交換所。\n使用期限：2024/11/14 23:59",
    "id": 99,
    "materialType": "common",
    "name": "橘色幸運之花",
    "seq": 10612
  },
  {
    "canUse": false,
    "flavorText": "因25點，Nightcord見。全體成員的心願而盛開的花朵。可使用於幸運之花遊行交換所。\n使用期限：2025/11/14 23:59",
    "id": 100,
    "materialType": "common",
    "name": "紫色幸運之花",
    "seq": 10613
  },
  {
    "canUse": false,
    "flavorText": "提升成員一歌技能的所需道具。",
    "id": 101,
    "materialType": "master_lesson",
    "name": "一歌的心願碎片",
    "seq": 10102
  },
  {
    "canUse": false,
    "flavorText": "提升成員咲希技能的所需道具。",
    "id": 102,
    "materialType": "master_lesson",
    "name": "咲希的心願碎片",
    "seq": 10103
  },
  {
    "canUse": false,
    "flavorText": "提升成員穗波技能的所需道具。",
    "id": 103,
    "materialType": "master_lesson",
    "name": "穗波的心願碎片",
    "seq": 10104
  },
  {
    "canUse": false,
    "flavorText": "提升成員志步技能的所需道具。",
    "id": 104,
    "materialType": "master_lesson",
    "name": "志步的心願碎片",
    "seq": 10105
  },
  {
    "canUse": false,
    "flavorText": "提升成員實乃理技能的所需道具。",
    "id": 105,
    "materialType": "master_lesson",
    "name": "實乃理的心願碎片",
    "seq": 10106
  },
  {
    "canUse": false,
    "flavorText": "提升成員遙技能的所需道具。",
    "id": 106,
    "materialType": "master_lesson",
    "name": "遙的心願碎片",
    "seq": 10107
  },
  {
    "canUse": false,
    "flavorText": "提升成員愛莉技能的所需道具。",
    "id": 107,
    "materialType": "master_lesson",
    "name": "愛莉的心願碎片",
    "seq": 10108
  },
  {
    "canUse": false,
    "flavorText": "提升成員雫技能的所需道具。",
    "id": 108,
    "materialType": "master_lesson",
    "name": "雫的心願碎片",
    "seq": 10109
  },
  {
    "canUse": false,
    "flavorText": "提升成員心羽技能的所需道具。",
    "id": 109,
    "materialType": "master_lesson",
    "name": "心羽的心願碎片",
    "seq": 10110
  },
  {
    "canUse": false,
    "flavorText": "提升成員杏技能的所需道具。",
    "id": 110,
    "materialType": "master_lesson",
    "name": "杏的心願碎片",
    "seq": 10111
  },
  {
    "canUse": false,
    "flavorText": "提升成員彰人技能的所需道具。",
    "id": 111,
    "materialType": "master_lesson",
    "name": "彰人的心願碎片",
    "seq": 10112
  },
  {
    "canUse": false,
    "flavorText": "提升成員冬彌技能的所需道具。",
    "id": 112,
    "materialType": "master_lesson",
    "name": "冬彌的心願碎片",
    "seq": 10113
  },
  {
    "canUse": false,
    "flavorText": "提升成員司技能的所需道具。",
    "id": 113,
    "materialType": "master_lesson",
    "name": "司的心願碎片",
    "seq": 10114
  },
  {
    "canUse": false,
    "flavorText": "提升成員笑夢技能的所需道具。",
    "id": 114,
    "materialType": "master_lesson",
    "name": "笑夢的心願碎片",
    "seq": 10115
  },
  {
    "canUse": false,
    "flavorText": "提升成員寧寧技能的所需道具。",
    "id": 115,
    "materialType": "master_lesson",
    "name": "寧寧的心願碎片",
    "seq": 10116
  },
  {
    "canUse": false,
    "flavorText": "提升成員類技能的所需道具。",
    "id": 116,
    "materialType": "master_lesson",
    "name": "類的心願碎片",
    "seq": 10117
  },
  {
    "canUse": false,
    "flavorText": "提升成員奏技能的所需道具。",
    "id": 117,
    "materialType": "master_lesson",
    "name": "奏的心願碎片",
    "seq": 10118
  },
  {
    "canUse": false,
    "flavorText": "提升成員真冬技能的所需道具。",
    "id": 118,
    "materialType": "master_lesson",
    "name": "真冬的心願碎片",
    "seq": 10119
  },
  {
    "canUse": false,
    "flavorText": "提升成員繪名技能的所需道具。",
    "id": 119,
    "materialType": "master_lesson",
    "name": "繪名的心願碎片",
    "seq": 10120
  },
  {
    "canUse": false,
    "flavorText": "提升成員瑞希技能的所需道具。",
    "id": 120,
    "materialType": "master_lesson",
    "name": "瑞希的心願碎片",
    "seq": 10121
  },
  {
    "canUse": false,
    "flavorText": "提升成員未來技能的所需道具。",
    "id": 121,
    "materialType": "master_lesson",
    "name": "初音未來的心願碎片",
    "seq": 10122
  },
  {
    "canUse": false,
    "flavorText": "提升成員鈴技能的所需道具。",
    "id": 122,
    "materialType": "master_lesson",
    "name": "鏡音鈴的心願碎片",
    "seq": 10123
  },
  {
    "canUse": false,
    "flavorText": "提升成員連技能的所需道具。",
    "id": 123,
    "materialType": "master_lesson",
    "name": "鏡音連的心願碎片",
    "seq": 10124
  },
  {
    "canUse": false,
    "flavorText": "提升成員流歌技能的所需道具。",
    "id": 124,
    "materialType": "master_lesson",
    "name": "巡音流歌的心願碎片",
    "seq": 10125
  },
  {
    "canUse": false,
    "flavorText": "提升成員MEIKO技能的所需道具。",
    "id": 125,
    "materialType": "master_lesson",
    "name": "MEIKO的心願碎片",
    "seq": 10126
  },
  {
    "canUse": false,
    "flavorText": "提升成員KAITO技能的所需道具。",
    "id": 126,
    "materialType": "master_lesson",
    "name": "KAITO的心願碎片",
    "seq": 10127
  },
  {
    "canUse": false,
    "flavorText": "提升Leo/need成員技能的所需道具。",
    "id": 127,
    "materialType": "master_lesson",
    "name": "Leo/need的心願碎片",
    "seq": 10128
  },
  {
    "canUse": false,
    "flavorText": "提升MORE MORE JUMP！成員技能的所需道具。",
    "id": 128,
    "materialType": "master_lesson",
    "name": "MORE MORE JUMP！的心願碎片",
    "seq": 10129
  },
  {
    "canUse": false,
    "flavorText": "提升Vivid BAD SQUAD成員技能的所需道具。",
    "id": 129,
    "materialType": "master_lesson",
    "name": "Vivid BAD SQUAD的心願碎片",
    "seq": 10130
  },
  {
    "canUse": false,
    "flavorText": "提升Wonderlands×Showtime成員技能的所需道具。",
    "id": 130,
    "materialType": "master_lesson",
    "name": "Wonderlands×Showtime的心願碎片",
    "seq": 10131
  },
  {
    "canUse": false,
    "flavorText": "提升25點，Nightcord見。成員技能的所需道具。",
    "id": 131,
    "materialType": "master_lesson",
    "name": "25點，Nightcord見。的心願碎片",
    "seq": 10132
  },
  {
    "canUse": false,
    "flavorText": "提升虛擬歌手成員技能的所需道具。",
    "id": 132,
    "materialType": "master_lesson",
    "name": "虛擬歌手的心願碎片",
    "seq": 10133
  },
  {
    "canUse": false,
    "flavorText": "提升成員一歌技能的所需道具。",
    "id": 133,
    "materialType": "master_lesson",
    "name": "一歌的心願純結晶",
    "seq": 10202
  },
  {
    "canUse": false,
    "flavorText": "提升成員咲希技能的所需道具。",
    "id": 134,
    "materialType": "master_lesson",
    "name": "咲希的心願純結晶",
    "seq": 10203
  },
  {
    "canUse": false,
    "flavorText": "提升成員穗波技能的所需道具。",
    "id": 135,
    "materialType": "master_lesson",
    "name": "穗波的心願純結晶",
    "seq": 10204
  },
  {
    "canUse": false,
    "flavorText": "提升成員志步技能的所需道具。",
    "id": 136,
    "materialType": "master_lesson",
    "name": "志步的心願純結晶",
    "seq": 10205
  },
  {
    "canUse": false,
    "flavorText": "提升成員實乃理技能的所需道具。",
    "id": 137,
    "materialType": "master_lesson",
    "name": "實乃理的心願純結晶",
    "seq": 10206
  },
  {
    "canUse": false,
    "flavorText": "提升成員遙技能的所需道具。",
    "id": 138,
    "materialType": "master_lesson",
    "name": "遙的心願純結晶",
    "seq": 10207
  },
  {
    "canUse": false,
    "flavorText": "提升成員愛莉技能的所需道具。",
    "id": 139,
    "materialType": "master_lesson",
    "name": "愛莉的心願純結晶",
    "seq": 10208
  },
  {
    "canUse": false,
    "flavorText": "提升成員雫技能的所需道具。",
    "id": 140,
    "materialType": "master_lesson",
    "name": "雫的心願純結晶",
    "seq": 10209
  },
  {
    "canUse": false,
    "flavorText": "提升成員心羽技能的所需道具。",
    "id": 141,
    "materialType": "master_lesson",
    "name": "心羽的心願純結晶",
    "seq": 10210
  },
  {
    "canUse": false,
    "flavorText": "提升成員杏技能的所需道具。",
    "id": 142,
    "materialType": "master_lesson",
    "name": "杏的心願純結晶",
    "seq": 10211
  },
  {
    "canUse": false,
    "flavorText": "提升成員彰人技能的所需道具。",
    "id": 143,
    "materialType": "master_lesson",
    "name": "彰人的心願純結晶",
    "seq": 10212
  },
  {
    "canUse": false,
    "flavorText": "提升成員冬彌技能的所需道具。",
    "id": 144,
    "materialType": "master_lesson",
    "name": "冬彌的心願純結晶",
    "seq": 10213
  },
  {
    "canUse": false,
    "flavorText": "提升成員司技能的所需道具。",
    "id": 145,
    "materialType": "master_lesson",
    "name": "司的心願純結晶",
    "seq": 10214
  },
  {
    "canUse": false,
    "flavorText": "提升成員笑夢技能的所需道具。",
    "id": 146,
    "materialType": "master_lesson",
    "name": "笑夢的心願純結晶",
    "seq": 10215
  },
  {
    "canUse": false,
    "flavorText": "提升成員寧寧技能的所需道具。",
    "id": 147,
    "materialType": "master_lesson",
    "name": "寧寧的心願純結晶",
    "seq": 10216
  },
  {
    "canUse": false,
    "flavorText": "提升成員類技能的所需道具。",
    "id": 148,
    "materialType": "master_lesson",
    "name": "類的心願純結晶",
    "seq": 10217
  },
  {
    "canUse": false,
    "flavorText": "提升成員奏技能的所需道具。",
    "id": 149,
    "materialType": "master_lesson",
    "name": "奏的心願純結晶",
    "seq": 10218
  },
  {
    "canUse": false,
    "flavorText": "提升成員真冬技能的所需道具。",
    "id": 150,
    "materialType": "master_lesson",
    "name": "真冬的心願純結晶",
    "seq": 10219
  },
  {
    "canUse": false,
    "flavorText": "提升成員繪名技能的所需道具。",
    "id": 151,
    "materialType": "master_lesson",
    "name": "繪名的心願純結晶",
    "seq": 10220
  },
  {
    "canUse": false,
    "flavorText": "提升成員瑞希技能的所需道具。",
    "id": 152,
    "materialType": "master_lesson",
    "name": "瑞希的心願純結晶",
    "seq": 10221
  },
  {
    "canUse": false,
    "flavorText": "提升成員未來技能的所需道具。",
    "id": 153,
    "materialType": "master_lesson",
    "name": "初音未來的心願純結晶",
    "seq": 10222
  },
  {
    "canUse": false,
    "flavorText": "提升成員鈴技能的所需道具。",
    "id": 154,
    "materialType": "master_lesson",
    "name": "鏡音鈴的心願純結晶",
    "seq": 10223
  },
  {
    "canUse": false,
    "flavorText": "提升成員連技能的所需道具。",
    "id": 155,
    "materialType": "master_lesson",
    "name": "鏡音連的心願純結晶",
    "seq": 10224
  },
  {
    "canUse": false,
    "flavorText": "提升成員流歌技能的所需道具。",
    "id": 156,
    "materialType": "master_lesson",
    "name": "巡音流歌的心願純結晶",
    "seq": 10225
  },
  {
    "canUse": false,
    "flavorText": "提升成員MEIKO技能的所需道具。",
    "id": 157,
    "materialType": "master_lesson",
    "name": "MEIKO的心願純結晶",
    "seq": 10226
  },
  {
    "canUse": false,
    "flavorText": "提升成員KAITO技能的所需道具。",
    "id": 158,
    "materialType": "master_lesson",
    "name": "KAITO的心願純結晶",
    "seq": 10227
  },
  {
    "canUse": false,
    "flavorText": "提升Leo/need成員技能的所需道具。",
    "id": 159,
    "materialType": "master_lesson",
    "name": "Leo/need的心願純結晶",
    "seq": 10228
  },
  {
    "canUse": false,
    "flavorText": "提升MORE MORE JUMP！成員技能的所需道具。",
    "id": 160,
    "materialType": "master_lesson",
    "name": "MORE MORE JUMP！的心願純結晶",
    "seq": 10229
  },
  {
    "canUse": false,
    "flavorText": "提升Vivid BAD SQUAD成員技能的所需道具。",
    "id": 161,
    "materialType": "master_lesson",
    "name": "Vivid BAD SQUAD的心願純結晶",
    "seq": 10230
  },
  {
    "canUse": false,
    "flavorText": "提升Wonderlands×Showtime成員技能的所需道具。",
    "id": 162,
    "materialType": "master_lesson",
    "name": "Wonderlands×Showtime的心願純結晶",
    "seq": 10231
  },
  {
    "canUse": false,
    "flavorText": "提升25點，Nightcord見。成員技能的所需道具。",
    "id": 163,
    "materialType": "master_lesson",
    "name": "25點，Nightcord見。的心願純結晶",
    "seq": 10232
  },
  {
    "canUse": false,
    "flavorText": "提升虛擬歌手成員技能的所需道具。",
    "id": 164,
    "materialType": "master_lesson",
    "name": "虛擬歌手的心願純結晶",
    "seq": 10233
  },
  {
    "canUse": false,
    "flavorText": "可在紀念★4成員劵交換所交換喜歡的★4成員。",
    "id": 165,
    "materialType": "card_ticket",
    "name": "紀念★4成員劵",
    "seq": 165
  },
  {
    "canUse": false,
    "flavorText": "因大家的心願而盛開的花朵。可使用於幸運之花遊行交換所。\n使用期限：2025/11/14 23:59",
    "id": 166,
    "materialType": "common",
    "name": "百變幸運之花",
    "seq": 10614
  },
  {
    "canUse": false,
    "flavorText": "可在[劇場版]★2成員券交換所交換喜歡的★2成員。",
    "id": 167,
    "materialType": "card_ticket",
    "name": "[劇場版]★2成員券",
    "seq": 165167
  },
  {
    "canUse": false,
    "flavorText": "閃耀著七彩光輝的回憶碎片。\n可用來交換特定記憶。",
    "id": 168,
    "materialType": "common",
    "name": "七彩記憶",
    "seq": 200000
  },
  {
    "canUse": false,
    "flavorText": "可兌換在「連線LIVE 特別版 世界計畫×偶像夢幻祭2 Ensemble in SEKAI」公演中發表之歌曲的連線LIVE ver. Vocal。",
    "id": 169,
    "materialType": "auto_exchange_music_vocal_ticket",
    "name": "「連線LIVE Ensemble in SEKAI」連線LIVE ver. Vocal兌換卡",
    "seq": 200001
  },
  {
    "canUse": false,
    "flavorText": "可至世界碎片交換所交換報酬。\n使用期限：2026/4/22 11:59",
    "id": 170,
    "materialType": "common",
    "name": "世界碎片",
    "seq": 10615
  },
  {
    "canUse": false,
    "flavorText": "可使用[4.5週年紀念]禮物券交換報酬。\n使用期限：2026/4/22 11:59",
    "id": 171,
    "materialType": "common",
    "name": "[4.5週年紀念]禮物券",
    "seq": 10616
  },
  {
    "canUse": false,
    "flavorText": "可兌換在「連線LIVE 25點，Nightcord見。×虛擬歌手 Dreamscape」公演中發表之歌曲的連線LIVE ver. Vocal。",
    "id": 172,
    "materialType": "auto_exchange_music_vocal_ticket",
    "name": "「連線LIVE Dreamscape」連線LIVE ver. Vocal兌換卡",
    "seq": 20002
  },
  {
    "canUse": false,
    "flavorText": "可至電子雞碎片交換所交換報酬。\n使用期限：2026/10/12 23:59",
    "id": 173,
    "materialType": "common",
    "name": "電子雞碎片",
    "seq": 10617
  },
  {
    "canUse": false,
    "flavorText": "為了栽種穗波慶祝生日的花時所需的露水。\n※僅能使用於2026年的生日活動。",
    "id": 176,
    "materialType": "birthday_party_delivery",
    "name": "慶典露水（虞美人紅）",
    "seq": 30003
  },
  {
    "canUse": false,
    "flavorText": "為了栽種遙慶祝生日的花時所需的露水。\n※僅能使用於2026年的生日活動。",
    "id": 179,
    "materialType": "birthday_party_delivery",
    "name": "慶典露水（肅穆藍）",
    "seq": 30006
  },
  {
    "canUse": false,
    "flavorText": "可至Bright Memories 活動交換所交換報酬。\n使用期限：2026/10/31 23:59",
    "id": 200,
    "materialType": "common",
    "name": "紅色旋律水滴",
    "seq": 10618
  },
  {
    "canUse": false,
    "flavorText": "可至Bright Memories 活動交換所交換報酬。\n使用期限：2026/10/31 23:59",
    "id": 201,
    "materialType": "common",
    "name": "藍色旋律水滴",
    "seq": 10619
  },
  {
    "canUse": false,
    "flavorText": "可至Bright Memories 活動交換所交換報酬。\n使用期限：2026/10/31 23:59",
    "id": 202,
    "materialType": "common",
    "name": "紫色旋律水滴",
    "seq": 10620
  },
  {
    "canUse": false,
    "flavorText": "可至Bright Memories 活動交換所交換報酬。\n使用期限：2026/10/31 23:59",
    "id": 203,
    "materialType": "common",
    "name": "彩虹旋律水滴",
    "seq": 10621
  },
  {
    "canUse": false,
    "flavorText": "限定期間內可於我的「世界」的「轉換器」使用。\n使用期限：2026/10/25 11:59",
    "id": 204,
    "materialType": "common",
    "name": "彩虹旋律",
    "seq": 10622
  },
  {
    "canUse": false,
    "flavorText": "可至金牌交換所交換報酬。\n使用期限：2026/10/31 23:59",
    "id": 211,
    "materialType": "common",
    "name": "金牌",
    "seq": 10623
  },
  {
    "canUse": false,
    "flavorText": "可在紀念★4成員券交換所交換喜歡的★4成員。",
    "id": 214,
    "materialType": "card_ticket",
    "name": "紀念★4成員券",
    "seq": 214
  },
  {
    "canUse": false,
    "flavorText": "可至紀念禮物券交換所交換報酬。\n使用期限：2026/11/30 11:59",
    "id": 215,
    "materialType": "common",
    "name": "紀念禮物券",
    "seq": 10625
  },
  {
    "canUse": false,
    "flavorText": "七彩通行證",
    "id": 1001,
    "materialType": "web_ticket",
    "name": "七彩通行證～BASIC～交換券",
    "seq": 1001
  },
  {
    "canUse": false,
    "flavorText": "高階任務通行證",
    "id": 1002,
    "materialType": "web_ticket",
    "name": "高階任務通行證交換券",
    "seq": 1002
  },
  {
    "canUse": false,
    "flavorText": "高階任務通行證（進階版）",
    "id": 1003,
    "materialType": "web_ticket",
    "name": "高階任務通行證交換券（進階版）",
    "seq": 1003
  },
  {
    "canUse": false,
    "flavorText": "七彩通行證",
    "id": 1004,
    "materialType": "web_ticket",
    "name": "七彩通行證～PRECIOUS～交換券",
    "seq": 1004
  },
  {
    "canUse": false,
    "flavorText": "我的「世界」任務通行證交換券",
    "id": 1005,
    "materialType": "web_ticket",
    "name": "我的「世界」任務通行證交換券",
    "seq": 1005
  },
  {
    "canUse": false,
    "flavorText": "高階任務通行證交換券（升級包）",
    "id": 1006,
    "materialType": "web_ticket",
    "name": "高階任務通行證交換券（升級包）",
    "seq": 1006
  },
  {
    "canUse": false,
    "flavorText": "[通行證組合包]高階任務通行證+我的「世界」任務通行證交換券",
    "id": 1009,
    "materialType": "web_ticket",
    "name": "通行證組合包交換券",
    "seq": 1009
  },
  {
    "canUse": false,
    "flavorText": "世界通行證交換券",
    "id": 1010,
    "materialType": "web_ticket",
    "name": "世界通行證交換券",
    "seq": 1010
  },
  {
    "canUse": false,
    "flavorText": "可用于升级回响称号",
    "id": 3002,
    "materialType": "common",
    "name": "回响点数",
    "seq": 90
  },
  {
    "canUse": false,
    "flavorText": "可在夏日兌換所交換喜歡的獎勵。",
    "id": 3005,
    "materialType": "common",
    "name": "派對徽章",
    "seq": 3005
  },
  {
    "canUse": false,
    "flavorText": "[劇場版]交換幣",
    "id": 4001,
    "materialType": "card_ticket",
    "name": "[劇場版]交換幣",
    "seq": 4001
  },
  {
    "canUse": false,
    "flavorText": "「摩爾加納像」設計圖的兌換券。",
    "id": 4002,
    "materialType": "common",
    "name": "「摩爾加納像」設計圖的兌換券。",
    "seq": 4002
  }
]