[
  {
    "gameCharacterUnitId": 1,
    "id": 1,
    "lua": "character_alone_action_1"
  },
  {
    "gameCharacterUnitId": 2,
    "id": 2,
    "lua": "character_alone_action_2"
  },
  {
    "gameCharacterUnitId": 3,
    "id": 3,
    "lua": "character_alone_action_3"
  },
  {
    "gameCharacterUnitId": 4,
    "id": 4,
    "lua": "character_alone_action_4"
  },
  {
    "gameCharacterUnitId": 5,
    "id": 5,
    "lua": "character_alone_action_5"
  },
  {
    "gameCharacterUnitId": 6,
    "id": 6,
    "lua": "character_alone_action_6"
  },
  {
    "gameCharacterUnitId": 7,
    "id": 7,
    "lua": "character_alone_action_7"
  },
  {
    "gameCharacterUnitId": 8,
    "id": 8,
    "lua": "character_alone_action_8"
  },
  {
    "gameCharacterUnitId": 9,
    "id": 9,
    "lua": "character_alone_action_9"
  },
  {
    "gameCharacterUnitId": 10,
    "id": 10,
    "lua": "character_alone_action_10"
  },
  {
    "gameCharacterUnitId": 11,
    "id": 11,
    "lua": "character_alone_action_11"
  },
  {
    "gameCharacterUnitId": 12,
    "id": 12,
    "lua": "character_alone_action_12"
  },
  {
    "gameCharacterUnitId": 13,
    "id": 13,
    "lua": "character_alone_action_13"
  },
  {
    "gameCharacterUnitId": 14,
    "id": 14,
    "lua": "character_alone_action_14"
  },
  {
    "gameCharacterUnitId": 15,
    "id": 15,
    "lua": "character_alone_action_15"
  },
  {
    "gameCharacterUnitId": 16,
    "id": 16,
    "lua": "character_alone_action_16"
  },
  {
    "gameCharacterUnitId": 17,
    "id": 17,
    "lua": "character_alone_action_17"
  },
  {
    "gameCharacterUnitId": 18,
    "id": 18,
    "lua": "character_alone_action_18"
  },
  {
    "gameCharacterUnitId": 19,
    "id": 19,
    "lua": "character_alone_action_19"
  },
  {
    "gameCharacterUnitId": 20,
    "id": 20,
    "lua": "character_alone_action_20"
  },
  {
    "gameCharacterUnitId": 27,
    "id": 27,
    "lua": "character_alone_action_27"
  },
  {
    "gameCharacterUnitId": 28,
    "id": 28,
    "lua": "character_alone_action_28"
  },
  {
    "gameCharacterUnitId": 29,
    "id": 29,
    "lua": "character_alone_action_29"
  },
  {
    "gameCharacterUnitId": 30,
    "id": 30,
    "lua": "character_alone_action_30"
  },
  {
    "gameCharacterUnitId": 31,
    "id": 31,
    "lua": "character_alone_action_31"
  },
  {
    "gameCharacterUnitId": 33,
    "id": 33,
    "lua": "character_alone_action_33"
  },
  {
    "gameCharacterUnitId": 39,
    "id": 39,
    "lua": "character_alone_action_39"
  },
  {
    "gameCharacterUnitId": 42,
    "id": 42,
    "lua": "character_alone_action_42"
  },
  {
    "gameCharacterUnitId": 49,
    "id": 49,
    "lua": "character_alone_action_49"
  },
  {
    "gameCharacterUnitId": 55,
    "id": 55,
    "lua": "character_alone_action_55"
  }
]