[
  {
    "assetbundleName": "small",
    "colorCode": "#ffffff",
    "displaySec": 1.0,
    "fromCost": 100,
    "id": 1,
    "messageLengthLimit": 8,
    "messageSize": "small",
    "resourceType": "jewel",
    "toCost": 299,
    "virtualLiveCheerMessageDisplayLimitId": 1,
    "virtualLiveType": "beginner"
  },
  {
    "assetbundleName": "medium",
    "colorCode": "#00ccbb",
    "displaySec": 2.0,
    "fromCost": 300,
    "id": 2,
    "messageLengthLimit": 16,
    "messageSize": "medium",
    "resourceType": "jewel",
    "toCost": 999,
    "virtualLiveCheerMessageDisplayLimitId": 2,
    "virtualLiveType": "beginner"
  },
  {
    "assetbundleName": "large",
    "colorCode": "#ffbb00",
    "displaySec": 3.0,
    "fromCost": 1000,
    "id": 3,
    "messageLengthLimit": 24,
    "messageSize": "large",
    "resourceType": "jewel",
    "toCost": 1999,
    "virtualLiveCheerMessageDisplayLimitId": 3,
    "virtualLiveType": "beginner"
  },
  {
    "assetbundleName": "xx_large",
    "colorCode": "#ff55aa",
    "displaySec": 10.0,
    "fromCost": 3000,
    "id": 4,
    "messageLengthLimit": 64,
    "messageSize": "xx_large",
    "resourceType": "jewel",
    "toCost": 50000,
    "virtualLiveCheerMessageDisplayLimitId": 4,
    "virtualLiveType": "beginner"
  },
  {
    "assetbundleName": "small",
    "colorCode": "#ffffff",
    "displaySec": 1.0,
    "fromCost": 100,
    "id": 5,
    "messageLengthLimit": 8,
    "messageSize": "small",
    "resourceType": "virtual_coin",
    "toCost": 999,
    "virtualLiveCheerMessageDisplayLimitId": 1,
    "virtualLiveType": "beginner"
  },
  {
    "assetbundleName": "medium",
    "colorCode": "#00ccbb",
    "displaySec": 2.0,
    "fromCost": 1000,
    "id": 6,
    "messageLengthLimit": 16,
    "messageSize": "medium",
    "resourceType": "virtual_coin",
    "toCost": 2999,
    "virtualLiveCheerMessageDisplayLimitId": 2,
    "virtualLiveType": "beginner"
  },
  {
    "assetbundleName": "large",
    "colorCode": "#ffbb00",
    "displaySec": 3.0,
    "fromCost": 3000,
    "id": 7,
    "messageLengthLimit": 24,
    "messageSize": "large",
    "resourceType": "virtual_coin",
    "toCost": 4999,
    "virtualLiveCheerMessageDisplayLimitId": 3,
    "virtualLiveType": "beginner"
  },
  {
    "assetbundleName": "xx_large",
    "colorCode": "#ff55aa",
    "displaySec": 10.0,
    "fromCost": 10000,
    "id": 8,
    "messageLengthLimit": 64,
    "messageSize": "xx_large",
    "resourceType": "virtual_coin",
    "toCost": 50000,
    "virtualLiveCheerMessageDisplayLimitId": 4,
    "virtualLiveType": "beginner"
  },
  {
    "assetbundleName": "small",
    "colorCode": "#ffffff",
    "displaySec": 1.0,
    "fromCost": 100,
    "id": 9,
    "messageLengthLimit": 8,
    "messageSize": "small",
    "resourceType": "jewel",
    "toCost": 299,
    "virtualLiveCheerMessageDisplayLimitId": 1,
    "virtualLiveType": "normal"
  },
  {
    "assetbundleName": "medium",
    "colorCode": "#00ccbb",
    "displaySec": 2.0,
    "fromCost": 300,
    "id": 10,
    "messageLengthLimit": 16,
    "messageSize": "medium",
    "resourceType": "jewel",
    "toCost": 999,
    "virtualLiveCheerMessageDisplayLimitId": 2,
    "virtualLiveType": "normal"
  },
  {
    "assetbundleName": "large",
    "colorCode": "#ffbb00",
    "displaySec": 3.0,
    "fromCost": 1000,
    "id": 11,
    "messageLengthLimit": 24,
    "messageSize": "large",
    "resourceType": "jewel",
    "toCost": 1999,
    "virtualLiveCheerMessageDisplayLimitId": 3,
    "virtualLiveType": "normal"
  },
  {
    "assetbundleName": "xx_large",
    "colorCode": "#ff55aa",
    "displaySec": 10.0,
    "fromCost": 3000,
    "id": 12,
    "messageLengthLimit": 64,
    "messageSize": "xx_large",
    "resourceType": "jewel",
    "toCost": 50000,
    "virtualLiveCheerMessageDisplayLimitId": 4,
    "virtualLiveType": "normal"
  },
  {
    "assetbundleName": "small",
    "colorCode": "#ffffff",
    "displaySec": 1.0,
    "fromCost": 100,
    "id": 13,
    "messageLengthLimit": 8,
    "messageSize": "small",
    "resourceType": "virtual_coin",
    "toCost": 999,
    "virtualLiveCheerMessageDisplayLimitId": 1,
    "virtualLiveType": "normal"
  },
  {
    "assetbundleName": "medium",
    "colorCode": "#00ccbb",
    "displaySec": 2.0,
    "fromCost": 1000,
    "id": 14,
    "messageLengthLimit": 16,
    "messageSize": "medium",
    "resourceType": "virtual_coin",
    "toCost": 2999,
    "virtualLiveCheerMessageDisplayLimitId": 2,
    "virtualLiveType": "normal"
  },
  {
    "assetbundleName": "large",
    "colorCode": "#ffbb00",
    "displaySec": 3.0,
    "fromCost": 3000,
    "id": 15,
    "messageLengthLimit": 24,
    "messageSize": "large",
    "resourceType": "virtual_coin",
    "toCost": 4999,
    "virtualLiveCheerMessageDisplayLimitId": 3,
    "virtualLiveType": "normal"
  },
  {
    "assetbundleName": "xx_large",
    "colorCode": "#ff55aa",
    "displaySec": 10.0,
    "fromCost": 10000,
    "id": 16,
    "messageLengthLimit": 64,
    "messageSize": "xx_large",
    "resourceType": "virtual_coin",
    "toCost": 50000,
    "virtualLiveCheerMessageDisplayLimitId": 4,
    "virtualLiveType": "normal"
  },
  {
    "assetbundleName": "small",
    "colorCode": "#ffffff",
    "displaySec": 1.0,
    "fromCost": 100,
    "id": 17,
    "messageLengthLimit": 8,
    "messageSize": "small",
    "resourceType": "jewel",
    "toCost": 299,
    "virtualLiveCheerMessageDisplayLimitId": 1,
    "virtualLiveType": "archive"
  },
  {
    "assetbundleName": "medium",
    "colorCode": "#00ccbb",
    "displaySec": 2.0,
    "fromCost": 300,
    "id": 18,
    "messageLengthLimit": 16,
    "messageSize": "medium",
    "resourceType": "jewel",
    "toCost": 999,
    "virtualLiveCheerMessageDisplayLimitId": 2,
    "virtualLiveType": "archive"
  },
  {
    "assetbundleName": "large",
    "colorCode": "#ffbb00",
    "displaySec": 3.0,
    "fromCost": 1000,
    "id": 19,
    "messageLengthLimit": 24,
    "messageSize": "large",
    "resourceType": "jewel",
    "toCost": 1999,
    "virtualLiveCheerMessageDisplayLimitId": 3,
    "virtualLiveType": "archive"
  },
  {
    "assetbundleName": "xx_large",
    "colorCode": "#ff55aa",
    "displaySec": 10.0,
    "fromCost": 3000,
    "id": 20,
    "messageLengthLimit": 64,
    "messageSize": "xx_large",
    "resourceType": "jewel",
    "toCost": 50000,
    "virtualLiveCheerMessageDisplayLimitId": 4,
    "virtualLiveType": "archive"
  },
  {
    "assetbundleName": "small",
    "colorCode": "#ffffff",
    "displaySec": 1.0,
    "fromCost": 100,
    "id": 21,
    "messageLengthLimit": 8,
    "messageSize": "small",
    "resourceType": "virtual_coin",
    "toCost": 999,
    "virtualLiveCheerMessageDisplayLimitId": 1,
    "virtualLiveType": "archive"
  },
  {
    "assetbundleName": "medium",
    "colorCode": "#00ccbb",
    "displaySec": 2.0,
    "fromCost": 1000,
    "id": 22,
    "messageLengthLimit": 16,
    "messageSize": "medium",
    "resourceType": "virtual_coin",
    "toCost": 2999,
    "virtualLiveCheerMessageDisplayLimitId": 2,
    "virtualLiveType": "archive"
  },
  {
    "assetbundleName": "large",
    "colorCode": "#ffbb00",
    "displaySec": 3.0,
    "fromCost": 3000,
    "id": 23,
    "messageLengthLimit": 24,
    "messageSize": "large",
    "resourceType": "virtual_coin",
    "toCost": 4999,
    "virtualLiveCheerMessageDisplayLimitId": 3,
    "virtualLiveType": "archive"
  },
  {
    "assetbundleName": "xx_large",
    "colorCode": "#ff55aa",
    "displaySec": 10.0,
    "fromCost": 10000,
    "id": 24,
    "messageLengthLimit": 64,
    "messageSize": "xx_large",
    "resourceType": "virtual_coin",
    "toCost": 50000,
    "virtualLiveCheerMessageDisplayLimitId": 4,
    "virtualLiveType": "archive"
  },
  {
    "assetbundleName": "small",
    "colorCode": "#ffffff",
    "displaySec": 1.0,
    "fromCost": 100,
    "id": 25,
    "messageLengthLimit": 8,
    "messageSize": "small",
    "resourceType": "jewel",
    "toCost": 299,
    "virtualLiveCheerMessageDisplayLimitId": 1,
    "virtualLiveType": "cheerful_carnival"
  },
  {
    "assetbundleName": "medium",
    "colorCode": "#00ccbb",
    "displaySec": 2.0,
    "fromCost": 300,
    "id": 26,
    "messageLengthLimit": 16,
    "messageSize": "medium",
    "resourceType": "jewel",
    "toCost": 999,
    "virtualLiveCheerMessageDisplayLimitId": 2,
    "virtualLiveType": "cheerful_carnival"
  },
  {
    "assetbundleName": "large",
    "colorCode": "#ffbb00",
    "displaySec": 3.0,
    "fromCost": 1000,
    "id": 27,
    "messageLengthLimit": 24,
    "messageSize": "large",
    "resourceType": "jewel",
    "toCost": 1999,
    "virtualLiveCheerMessageDisplayLimitId": 3,
    "virtualLiveType": "cheerful_carnival"
  },
  {
    "assetbundleName": "xx_large",
    "colorCode": "#ff55aa",
    "displaySec": 10.0,
    "fromCost": 3000,
    "id": 28,
    "messageLengthLimit": 64,
    "messageSize": "xx_large",
    "resourceType": "jewel",
    "toCost": 50000,
    "virtualLiveCheerMessageDisplayLimitId": 4,
    "virtualLiveType": "cheerful_carnival"
  },
  {
    "assetbundleName": "small",
    "colorCode": "#ffffff",
    "displaySec": 1.0,
    "fromCost": 100,
    "id": 29,
    "messageLengthLimit": 8,
    "messageSize": "small",
    "resourceType": "virtual_coin",
    "toCost": 999,
    "virtualLiveCheerMessageDisplayLimitId": 1,
    "virtualLiveType": "cheerful_carnival"
  },
  {
    "assetbundleName": "medium",
    "colorCode": "#00ccbb",
    "displaySec": 2.0,
    "fromCost": 1000,
    "id": 30,
    "messageLengthLimit": 16,
    "messageSize": "medium",
    "resourceType": "virtual_coin",
    "toCost": 2999,
    "virtualLiveCheerMessageDisplayLimitId": 2,
    "virtualLiveType": "cheerful_carnival"
  },
  {
    "assetbundleName": "large",
    "colorCode": "#ffbb00",
    "displaySec": 3.0,
    "fromCost": 3000,
    "id": 31,
    "messageLengthLimit": 24,
    "messageSize": "large",
    "resourceType": "virtual_coin",
    "toCost": 4999,
    "virtualLiveCheerMessageDisplayLimitId": 3,
    "virtualLiveType": "cheerful_carnival"
  },
  {
    "assetbundleName": "xx_large",
    "colorCode": "#ff55aa",
    "displaySec": 10.0,
    "fromCost": 10000,
    "id": 32,
    "messageLengthLimit": 64,
    "messageSize": "xx_large",
    "resourceType": "virtual_coin",
    "toCost": 50000,
    "virtualLiveCheerMessageDisplayLimitId": 4,
    "virtualLiveType": "cheerful_carnival"
  },
  {
    "assetbundleName": "small",
    "colorCode": "#ffffff",
    "displaySec": 1.0,
    "fromCost": 100,
    "id": 33,
    "messageLengthLimit": 8,
    "messageSize": "small",
    "resourceType": "jewel",
    "toCost": 299,
    "virtualLiveCheerMessageDisplayLimitId": 1,
    "virtualLiveType": "streaming"
  },
  {
    "assetbundleName": "medium",
    "colorCode": "#00ccbb",
    "displaySec": 2.0,
    "fromCost": 300,
    "id": 34,
    "messageLengthLimit": 16,
    "messageSize": "medium",
    "resourceType": "jewel",
    "toCost": 999,
    "virtualLiveCheerMessageDisplayLimitId": 2,
    "virtualLiveType": "streaming"
  },
  {
    "assetbundleName": "large",
    "colorCode": "#ffbb00",
    "displaySec": 3.0,
    "fromCost": 1000,
    "id": 35,
    "messageLengthLimit": 24,
    "messageSize": "large",
    "resourceType": "jewel",
    "toCost": 1999,
    "virtualLiveCheerMessageDisplayLimitId": 3,
    "virtualLiveType": "streaming"
  },
  {
    "assetbundleName": "xx_large",
    "colorCode": "#ff55aa",
    "displaySec": 10.0,
    "fromCost": 3000,
    "id": 36,
    "messageLengthLimit": 64,
    "messageSize": "xx_large",
    "resourceType": "jewel",
    "toCost": 50000,
    "virtualLiveCheerMessageDisplayLimitId": 4,
    "virtualLiveType": "streaming"
  },
  {
    "assetbundleName": "small",
    "colorCode": "#ffffff",
    "displaySec": 1.0,
    "fromCost": 100,
    "id": 37,
    "messageLengthLimit": 8,
    "messageSize": "small",
    "resourceType": "virtual_coin",
    "toCost": 999,
    "virtualLiveCheerMessageDisplayLimitId": 1,
    "virtualLiveType": "streaming"
  },
  {
    "assetbundleName": "medium",
    "colorCode": "#00ccbb",
    "displaySec": 2.0,
    "fromCost": 1000,
    "id": 38,
    "messageLengthLimit": 16,
    "messageSize": "medium",
    "resourceType": "virtual_coin",
    "toCost": 2999,
    "virtualLiveCheerMessageDisplayLimitId": 2,
    "virtualLiveType": "streaming"
  },
  {
    "assetbundleName": "large",
    "colorCode": "#ffbb00",
    "displaySec": 3.0,
    "fromCost": 3000,
    "id": 39,
    "messageLengthLimit": 24,
    "messageSize": "large",
    "resourceType": "virtual_coin",
    "toCost": 4999,
    "virtualLiveCheerMessageDisplayLimitId": 3,
    "virtualLiveType": "streaming"
  },
  {
    "assetbundleName": "xx_large",
    "colorCode": "#ff55aa",
    "displaySec": 10.0,
    "fromCost": 10000,
    "id": 40,
    "messageLengthLimit": 64,
    "messageSize": "xx_large",
    "resourceType": "virtual_coin",
    "toCost": 50000,
    "virtualLiveCheerMessageDisplayLimitId": 4,
    "virtualLiveType": "streaming"
  },
  {
    "assetbundleName": "x_large",
    "colorCode": "#ff7722",
    "displaySec": 5.0,
    "fromCost": 2000,
    "id": 41,
    "messageLengthLimit": 32,
    "messageSize": "x_large",
    "resourceType": "jewel",
    "toCost": 2999,
    "virtualLiveCheerMessageDisplayLimitId": 5,
    "virtualLiveType": "beginner"
  },
  {
    "assetbundleName": "x_large",
    "colorCode": "#ff7722",
    "displaySec": 5.0,
    "fromCost": 5000,
    "id": 42,
    "messageLengthLimit": 32,
    "messageSize": "x_large",
    "resourceType": "virtual_coin",
    "toCost": 9999,
    "virtualLiveCheerMessageDisplayLimitId": 5,
    "virtualLiveType": "beginner"
  },
  {
    "assetbundleName": "x_large",
    "colorCode": "#ff7722",
    "displaySec": 5.0,
    "fromCost": 2000,
    "id": 43,
    "messageLengthLimit": 32,
    "messageSize": "x_large",
    "resourceType": "jewel",
    "toCost": 2999,
    "virtualLiveCheerMessageDisplayLimitId": 5,
    "virtualLiveType": "normal"
  },
  {
    "assetbundleName": "x_large",
    "colorCode": "#ff7722",
    "displaySec": 5.0,
    "fromCost": 5000,
    "id": 44,
    "messageLengthLimit": 32,
    "messageSize": "x_large",
    "resourceType": "virtual_coin",
    "toCost": 9999,
    "virtualLiveCheerMessageDisplayLimitId": 5,
    "virtualLiveType": "normal"
  },
  {
    "assetbundleName": "x_large",
    "colorCode": "#ff7722",
    "displaySec": 5.0,
    "fromCost": 2000,
    "id": 45,
    "messageLengthLimit": 32,
    "messageSize": "x_large",
    "resourceType": "jewel",
    "toCost": 2999,
    "virtualLiveCheerMessageDisplayLimitId": 5,
    "virtualLiveType": "archive"
  },
  {
    "assetbundleName": "x_large",
    "colorCode": "#ff7722",
    "displaySec": 5.0,
    "fromCost": 5000,
    "id": 46,
    "messageLengthLimit": 32,
    "messageSize": "x_large",
    "resourceType": "virtual_coin",
    "toCost": 9999,
    "virtualLiveCheerMessageDisplayLimitId": 5,
    "virtualLiveType": "archive"
  },
  {
    "assetbundleName": "x_large",
    "colorCode": "#ff7722",
    "displaySec": 5.0,
    "fromCost": 2000,
    "id": 47,
    "messageLengthLimit": 32,
    "messageSize": "x_large",
    "resourceType": "jewel",
    "toCost": 2999,
    "virtualLiveCheerMessageDisplayLimitId": 5,
    "virtualLiveType": "cheerful_carnival"
  },
  {
    "assetbundleName": "x_large",
    "colorCode": "#ff7722",
    "displaySec": 5.0,
    "fromCost": 5000,
    "id": 48,
    "messageLengthLimit": 32,
    "messageSize": "x_large",
    "resourceType": "virtual_coin",
    "toCost": 9999,
    "virtualLiveCheerMessageDisplayLimitId": 5,
    "virtualLiveType": "cheerful_carnival"
  },
  {
    "assetbundleName": "x_large",
    "colorCode": "#ff7722",
    "displaySec": 5.0,
    "fromCost": 2000,
    "id": 49,
    "messageLengthLimit": 32,
    "messageSize": "x_large",
    "resourceType": "jewel",
    "toCost": 2999,
    "virtualLiveCheerMessageDisplayLimitId": 5,
    "virtualLiveType": "streaming"
  },
  {
    "assetbundleName": "x_large",
    "colorCode": "#ff7722",
    "displaySec": 5.0,
    "fromCost": 5000,
    "id": 50,
    "messageLengthLimit": 32,
    "messageSize": "x_large",
    "resourceType": "virtual_coin",
    "toCost": 9999,
    "virtualLiveCheerMessageDisplayLimitId": 5,
    "virtualLiveType": "streaming"
  }
]